DexonlineParser/__init__.py
DexonlineParser/parser.py
dexonlineparser-0.0.6.dist-info/METADATA
dexonlineparser-0.0.6.dist-info/WHEEL
dexonlineparser-0.0.6.dist-info/licenses/LICENSE
dexonlineparser-0.0.6.dist-info/RECORD
